hangul_keyboard/__init__.py
hangul_keyboard/core.py
hangul_keyboard/mapping.py
hangul_keyboard-0.3.1.dist-info/METADATA
hangul_keyboard-0.3.1.dist-info/WHEEL
hangul_keyboard-0.3.1.dist-info/top_level.txt
hangul_keyboard-0.3.1.dist-info/RECORD
