Metadata-Version: 2.4
Name: hangul-keyboard
Version: 0.3.1
Summary: Korean Hangul keyboard-based English to Korean converter
Home-page: https://github.com/backend-kms/hangul-keyboard
Author: Kasie
Author-email: cod.kms@gmail.com
License: MIT
Keywords: hangul korean keyboard typo search django
Classifier: Programming Language :: Python :: 3
Classifier: Programming Language :: Python :: 3.8
Classifier: Programming Language :: Python :: 3.9
Classifier: Programming Language :: Python :: 3.10
Classifier: Programming Language :: Python :: 3.11
Classifier: License :: OSI Approved :: MIT License
Classifier: Operating System :: OS Independent
Requires-Python: >=3.8
Provides-Extra: dev
Requires-Dist: pytest>=7.0; extra == "dev"
Requires-Dist: pytest-cov>=3.0; extra == "dev"
